{
	"Store":{
		"freshSell":[{
			"images":"img/002.jpg"
		},{
			"images":"img/003.jpg"
		},{
			"images":"img/004.jpg"
		},{
			"images":"img/005.jpg"
		}],
		"Recommend":[{
			"images":"img/006.jpg"
		},{
			"images":"img/007.jpg"
		},{
			"images":"img/008.jpg"
		},{
			"images":"img/009.jpg"
		},{
			"images":"img/010.jpg"
		},{
			"images":"img/011.jpg"
		}],
		"shootingEquipment":[{
			"images":"img/012.jpg",
			"title":"EOS99D",
			"price":"6060"
		},{
			"images":"img/013.jpg",
			"title":"EOS19D",
			"price":"2060"
		},{
			"images":"img/014.jpg",
			"title":"EOS29D",
			"price":"4060"
		},{
			"images":"img/015.jpg",
			"title":"EOS39D",
			"price":"3060"
		},{
			"images":"img/016.jpg",
			"title":"EOS49D",
			"price":"6060"
		},{
			"images":"img/017.jpg",
			"title":"EOS59D",
			"price":"7060"
		}]
	}
}
